{
  "modelVersion" : "2.2",
  "id" : "deployRelease",
  "name" : "deployRelease",
  "lastUpdate" : 1645112468130,
  "rows" : [
    [
      {
        "type" : "container",
        "dimension" : {
          "xs" : 12
        },
        "propertyValues" : { },
        "reference" : "62d28868-e4e1-4e68-af37-bf7dbd996640",
        "hasValidationError" : false,
        "id" : "pbContainer",
        "rows" : [
          [
            {
              "type" : "component",
              "dimension" : {
                "md" : 12,
                "sm" : 12,
                "xs" : 12,
                "lg" : 12
              },
              "propertyValues" : {
                "hidden" : {
                  "type" : "constant",
                  "value" : false
                },
                "level" : {
                  "type" : "constant",
                  "value" : "Level 1"
                },
                "cssClasses" : {
                  "type" : "constant",
                  "value" : ""
                },
                "text" : {
                  "type" : "interpolation",
                  "value" : "{{ task.displayName }}"
                },
                "alignment" : {
                  "type" : "constant",
                  "value" : "center"
                },
                "dimension" : {
                  "type" : "constant",
                  "value" : 12
                }
              },
              "reference" : "4e03679d-7885-46b1-9242-fa08297dd92b",
              "hasValidationError" : false,
              "id" : "pbTitle",
              "description" : ""
            }
          ],
          [
            {
              "type" : "component",
              "dimension" : {
                "md" : 12,
                "sm" : 12,
                "xs" : 12,
                "lg" : 12
              },
              "propertyValues" : {
                "allowHtml" : {
                  "type" : "constant",
                  "value" : true
                },
                "labelHidden" : {
                  "type" : "constant",
                  "value" : true
                },
                "hidden" : {
                  "type" : "constant",
                  "value" : false
                },
                "cssClasses" : {
                  "type" : "constant",
                  "value" : ""
                },
                "label" : {
                  "type" : "interpolation"
                },
                "text" : {
                  "type" : "interpolation",
                  "value" : "{{ task.displayDescription }}"
                },
                "alignment" : {
                  "type" : "constant",
                  "value" : "left"
                },
                "dimension" : {
                  "type" : "constant",
                  "value" : 12
                }
              },
              "reference" : "031dcbd3-8a5b-49bb-b85e-dd742f58776b",
              "hasValidationError" : false,
              "id" : "pbText",
              "description" : ""
            }
          ]
        ]
      }
    ],
    [
      {
        "type" : "formContainer",
        "dimension" : {
          "xs" : 12
        },
        "propertyValues" : { },
        "reference" : "99be01c6-c780-4b17-a32f-c753193b97ea",
        "hasValidationError" : false,
        "id" : "pbFormContainer",
        "container" : {
          "type" : "container",
          "dimension" : {
            "xs" : 12
          },
          "propertyValues" : { },
          "reference" : "5e10ff79-76b8-476c-9694-758bcac2f37a",
          "hasValidationError" : false,
          "id" : "pbContainer",
          "rows" : [
            [
              {
                "type" : "component",
                "dimension" : {
                  "md" : 12,
                  "sm" : 12,
                  "xs" : 12,
                  "lg" : 12
                },
                "propertyValues" : {
                  "hidden" : {
                    "type" : "constant",
                    "value" : false
                  },
                  "level" : {
                    "type" : "constant",
                    "value" : "Level 4"
                  },
                  "cssClasses" : {
                    "type" : "constant",
                    "value" : ""
                  },
                  "text" : {
                    "type" : "interpolation",
                    "value" : "Patch"
                  },
                  "alignment" : {
                    "type" : "constant",
                    "value" : "left"
                  },
                  "dimension" : {
                    "type" : "constant",
                    "value" : 12
                  }
                },
                "reference" : "8f5d4b5d-c7f3-40d4-b8f0-eccc1015c8cb",
                "hasValidationError" : false,
                "id" : "pbTitle",
                "description" : ""
              }
            ],
            [
              {
                "type" : "container",
                "dimension" : {
                  "md" : 12,
                  "sm" : 12,
                  "xs" : 12,
                  "lg" : 12
                },
                "propertyValues" : {
                  "repeatedCollection" : {
                    "type" : "variable"
                  },
                  "hidden" : {
                    "type" : "constant",
                    "value" : false
                  },
                  "cssClasses" : {
                    "type" : "constant",
                    "value" : ""
                  },
                  "dimension" : {
                    "type" : "constant",
                    "value" : 12
                  }
                },
                "reference" : "b7cdf30c-0d17-4968-a5c8-96f9053d715b",
                "hasValidationError" : false,
                "id" : "pbContainer",
                "rows" : [
                  [
                    {
                      "type" : "component",
                      "dimension" : {
                        "md" : 12,
                        "sm" : 12,
                        "xs" : 12,
                        "lg" : 12
                      },
                      "propertyValues" : {
                        "allowHtml" : {
                          "type" : "constant",
                          "value" : true
                        },
                        "labelHidden" : {
                          "type" : "constant",
                          "value" : false
                        },
                        "hidden" : {
                          "type" : "expression",
                          "value" : "!patch.version"
                        },
                        "cssClasses" : {
                          "type" : "constant",
                          "value" : ""
                        },
                        "label" : {
                          "type" : "interpolation",
                          "value" : "Version"
                        },
                        "text" : {
                          "type" : "interpolation",
                          "value" : "{{patch.version}}"
                        },
                        "alignment" : {
                          "type" : "constant",
                          "value" : "left"
                        },
                        "dimension" : {
                          "type" : "constant",
                          "value" : 12
                        }
                      },
                      "reference" : "6ba47dbe-a876-46c0-bbae-2c9c36b42513",
                      "hasValidationError" : false,
                      "id" : "pbText",
                      "description" : ""
                    }
                  ],
                  [
                    {
                      "type" : "component",
                      "dimension" : {
                        "md" : 12,
                        "sm" : 12,
                        "xs" : 12,
                        "lg" : 12
                      },
                      "propertyValues" : {
                        "allowHtml" : {
                          "type" : "constant",
                          "value" : true
                        },
                        "labelHidden" : {
                          "type" : "constant",
                          "value" : false
                        },
                        "hidden" : {
                          "type" : "expression",
                          "value" : "!patch.description"
                        },
                        "cssClasses" : {
                          "type" : "constant",
                          "value" : ""
                        },
                        "label" : {
                          "type" : "interpolation",
                          "value" : "Description"
                        },
                        "text" : {
                          "type" : "interpolation",
                          "value" : "{{patch.description}}"
                        },
                        "alignment" : {
                          "type" : "constant",
                          "value" : "left"
                        },
                        "dimension" : {
                          "type" : "constant",
                          "value" : 12
                        }
                      },
                      "reference" : "60dbd19f-4ace-460c-9031-2c7a02ca2069",
                      "hasValidationError" : false,
                      "id" : "pbText",
                      "description" : ""
                    }
                  ],
                  [
                    {
                      "type" : "component",
                      "dimension" : {
                        "md" : 12,
                        "sm" : 12,
                        "xs" : 12,
                        "lg" : 12
                      },
                      "propertyValues" : {
                        "hidden" : {
                          "type" : "constant",
                          "value" : false
                        },
                        "level" : {
                          "type" : "constant",
                          "value" : "Level 4"
                        },
                        "cssClasses" : {
                          "type" : "constant",
                          "value" : ""
                        },
                        "text" : {
                          "type" : "interpolation",
                          "value" : "List Fixed Bugs"
                        },
                        "alignment" : {
                          "type" : "constant",
                          "value" : "left"
                        },
                        "dimension" : {
                          "type" : "constant",
                          "value" : 12
                        }
                      },
                      "reference" : "0d7e9f7a-6f43-4f82-90c9-906926fad576",
                      "hasValidationError" : false,
                      "id" : "pbTitle",
                      "description" : ""
                    }
                  ],
                  [
                    {
                      "type" : "container",
                      "dimension" : {
                        "md" : 12,
                        "sm" : 12,
                        "xs" : 12,
                        "lg" : 12
                      },
                      "propertyValues" : {
                        "repeatedCollection" : {
                          "type" : "variable",
                          "value" : "patch_listFixedBugs"
                        },
                        "hidden" : {
                          "type" : "constant",
                          "value" : false
                        },
                        "cssClasses" : {
                          "type" : "constant",
                          "value" : ""
                        },
                        "dimension" : {
                          "type" : "constant",
                          "value" : 12
                        }
                      },
                      "reference" : "d4132e7b-5f94-4ef9-b8be-c9cbf54f4016",
                      "hasValidationError" : false,
                      "id" : "pbContainer",
                      "rows" : [
                        [
                          {
                            "type" : "component",
                            "dimension" : {
                              "md" : 12,
                              "sm" : 12,
                              "xs" : 12,
                              "lg" : 12
                            },
                            "propertyValues" : {
                              "labelHidden" : {
                                "type" : "constant",
                                "value" : false
                              },
                              "hidden" : {
                                "type" : "constant",
                                "value" : false
                              },
                              "labelPosition" : {
                                "type" : "constant",
                                "value" : "top"
                              },
                              "cssClasses" : {
                                "type" : "constant",
                                "value" : ""
                              },
                              "availableValues" : {
                                "type" : "expression",
                                "value" : "bug_query"
                              },
                              "labelWidth" : {
                                "type" : "constant",
                                "value" : 1
                              },
                              "label" : {
                                "type" : "interpolation",
                                "value" : "List Fixed Bugs"
                              },
                              "placeholder" : {
                                "type" : "constant",
                                "value" : "Select a List Fixed Bugs"
                              },
                              "dimension" : {
                                "type" : "constant",
                                "value" : 12
                              },
                              "value" : {
                                "type" : "variable",
                                "value" : "$item"
                              },
                              "required" : {
                                "type" : "constant",
                                "value" : true
                              }
                            },
                            "reference" : "257ae1fd-79c4-4abd-826a-0b8870ff8eff",
                            "hasValidationError" : false,
                            "id" : "pbSelect",
                            "description" : ""
                          }
                        ],
                        [
                          {
                            "type" : "component",
                            "dimension" : {
                              "md" : 12,
                              "sm" : 12,
                              "xs" : 12,
                              "lg" : 12
                            },
                            "propertyValues" : {
                              "removeItem" : {
                                "type" : "variable",
                                "value" : "$item"
                              },
                              "hidden" : {
                                "type" : "constant",
                                "value" : false
                              },
                              "cssClasses" : {
                                "type" : "constant",
                                "value" : ""
                              },
                              "buttonStyle" : {
                                "type" : "constant",
                                "value" : "danger"
                              },
                              "label" : {
                                "type" : "interpolation",
                                "value" : "<span class=\"glyphicon glyphicon-remove\"></span>"
                              },
                              "dataToSend" : {
                                "type" : "expression"
                              },
                              "labelHidden" : {
                                "type" : "constant",
                                "value" : false
                              },
                              "collectionPosition" : {
                                "type" : "constant",
                                "value" : "Item"
                              },
                              "targetUrlOnSuccess" : {
                                "type" : "interpolation"
                              },
                              "action" : {
                                "type" : "constant",
                                "value" : "Remove from collection"
                              },
                              "collectionToModify" : {
                                "type" : "variable",
                                "value" : "$collection"
                              },
                              "valueToAdd" : {
                                "type" : "expression"
                              },
                              "disabled" : {
                                "type" : "constant",
                                "value" : false
                              },
                              "alignment" : {
                                "type" : "constant",
                                "value" : "right"
                              },
                              "dimension" : {
                                "type" : "constant",
                                "value" : 12
                              }
                            },
                            "reference" : "0f64601a-8240-4232-a324-aa05ce16d742",
                            "hasValidationError" : false,
                            "id" : "pbButton",
                            "description" : ""
                          }
                        ]
                      ]
                    }
                  ],
                  [
                    {
                      "type" : "component",
                      "dimension" : {
                        "md" : 12,
                        "sm" : 12,
                        "xs" : 12,
                        "lg" : 12
                      },
                      "propertyValues" : {
                        "removeItem" : {
                          "type" : "variable"
                        },
                        "hidden" : {
                          "type" : "constant",
                          "value" : false
                        },
                        "cssClasses" : {
                          "type" : "constant",
                          "value" : ""
                        },
                        "buttonStyle" : {
                          "type" : "constant",
                          "value" : "primary"
                        },
                        "label" : {
                          "type" : "interpolation",
                          "value" : "<span class=\"glyphicon glyphicon-plus\"></span> Add Bug"
                        },
                        "dataToSend" : {
                          "type" : "expression"
                        },
                        "labelHidden" : {
                          "type" : "constant",
                          "value" : false
                        },
                        "collectionPosition" : {
                          "type" : "constant"
                        },
                        "targetUrlOnSuccess" : {
                          "type" : "interpolation"
                        },
                        "action" : {
                          "type" : "constant",
                          "value" : "Add to collection"
                        },
                        "collectionToModify" : {
                          "type" : "variable",
                          "value" : "patch_listFixedBugs"
                        },
                        "valueToAdd" : {
                          "type" : "expression",
                          "value" : "{\r\n  \"persistenceId_string\" : \"\",\r\n  \"description\" : \"\",\r\n  \"dateSubmitted\" : null,\r\n  \"idTicket\" : \"\",\r\n  \"status\" : \"\"\r\n}"
                        },
                        "disabled" : {
                          "type" : "constant",
                          "value" : false
                        },
                        "alignment" : {
                          "type" : "constant",
                          "value" : "left"
                        },
                        "dimension" : {
                          "type" : "constant",
                          "value" : 12
                        }
                      },
                      "reference" : "87b882aa-d1ce-4a6c-9ba4-78e529305643",
                      "hasValidationError" : false,
                      "id" : "pbButton",
                      "description" : ""
                    }
                  ]
                ]
              }
            ],
            [
              {
                "type" : "component",
                "dimension" : {
                  "md" : 12,
                  "sm" : 12,
                  "xs" : 12,
                  "lg" : 12
                },
                "propertyValues" : {
                  "removeItem" : {
                    "type" : "variable"
                  },
                  "hidden" : {
                    "type" : "constant",
                    "value" : false
                  },
                  "cssClasses" : {
                    "type" : "constant",
                    "value" : ""
                  },
                  "buttonStyle" : {
                    "type" : "constant",
                    "value" : "primary"
                  },
                  "label" : {
                    "type" : "interpolation",
                    "value" : "Submit"
                  },
                  "dataToSend" : {
                    "type" : "expression",
                    "value" : "formOutput"
                  },
                  "dataFromError" : {
                    "type" : "variable",
                    "value" : "formOutput._submitError"
                  },
                  "labelHidden" : {
                    "type" : "constant",
                    "value" : false
                  },
                  "collectionPosition" : {
                    "type" : "constant"
                  },
                  "targetUrlOnSuccess" : {
                    "type" : "interpolation",
                    "value" : "/bonita"
                  },
                  "action" : {
                    "type" : "constant",
                    "value" : "Submit task"
                  },
                  "collectionToModify" : {
                    "type" : "variable"
                  },
                  "valueToAdd" : {
                    "type" : "expression"
                  },
                  "disabled" : {
                    "type" : "expression",
                    "value" : "$form.$invalid"
                  },
                  "alignment" : {
                    "type" : "constant",
                    "value" : "center"
                  },
                  "dimension" : {
                    "type" : "constant",
                    "value" : 12
                  }
                },
                "reference" : "2da46654-085e-46e5-a14c-b6edb74ac94e",
                "hasValidationError" : false,
                "id" : "pbButton",
                "description" : ""
              }
            ],
            [
              {
                "type" : "component",
                "dimension" : {
                  "md" : 12,
                  "sm" : 12,
                  "xs" : 12,
                  "lg" : 12
                },
                "propertyValues" : {
                  "allowHTML" : {
                    "type" : "constant",
                    "value" : true
                  },
                  "allowHtml" : {
                    "type" : "constant",
                    "value" : true
                  },
                  "labelHidden" : {
                    "type" : "constant",
                    "value" : true
                  },
                  "hidden" : {
                    "type" : "expression",
                    "value" : "!formOutput._submitError.message"
                  },
                  "cssClasses" : {
                    "type" : "constant",
                    "value" : "alert alert-danger col-lg-6 col-lg-offset-3"
                  },
                  "label" : {
                    "type" : "interpolation"
                  },
                  "text" : {
                    "type" : "interpolation",
                    "value" : "<strong>Debug message</strong>\n<br/>\n{{formOutput._submitError.message}}\n{{submit_errors_list}}"
                  },
                  "alignment" : {
                    "type" : "constant",
                    "value" : "left"
                  },
                  "dimension" : {
                    "type" : "constant",
                    "value" : 12
                  }
                },
                "reference" : "05656097-a27b-40e4-83e3-35a4b28a988c",
                "hasValidationError" : false,
                "id" : "pbText",
                "description" : ""
              }
            ]
          ]
        }
      }
    ]
  ],
  "assets" : [
    {
      "id" : "f3182914-f9d0-40df-a5af-f46c7cf001f3",
      "name" : "style.css",
      "type" : "css",
      "order" : 0,
      "external" : false
    },
    {
      "id" : "bb523278-8b24-48d7-860f-67e57da4dc08",
      "name" : "localization.json",
      "type" : "json",
      "order" : 0,
      "external" : false
    }
  ],
  "inactiveAssets" : [ ],
  "variables" : {
    "patch" : {
      "type" : "url",
      "value" : [
        "../{{context.patch_ref.link}}"
      ],
      "exposed" : false
    },
    "task" : {
      "type" : "url",
      "value" : [
        "../API/bpm/userTask/{{taskId}}"
      ],
      "exposed" : false
    },
    "bug_query" : {
      "type" : "url",
      "value" : [
        "../API/bdm/businessData/com.bugs.model.Bug?q=find&p=0&c=99"
      ],
      "exposed" : false
    },
    "submit_errors_list" : {
      "type" : "expression",
      "value" : [
        "if($data.formOutput && $data.formOutput._submitError && $data.formOutput._submitError.explanations){",
        "\tconst liElements = $data.formOutput._submitError.explanations",
        "\t\t.filter(cause => cause !== null)",
        "\t\t.map(cause => \"<li>\" + cause + \"</li>\")",
        "\t\t.join('');",
        "\tif(liElements){",
        "\t\treturn \"<ul>\" + liElements + \"</ul>\";",
        "\t}",
        "}"
      ],
      "exposed" : false
    },
    "formOutput" : {
      "type" : "expression",
      "value" : [
        "if( $data.patch && $data.patch_listFixedBugs ){",
        "\t//attach lazy references variables to parent variables",
        "\t$data.patch.listFixedBugs = $data.patch_listFixedBugs;",
        "\treturn {",
        "\t\t//map patch variable to expected task contract input",
        "\t\tpatchInput: {",
        "\t\t\tlistFixedBugs: $data.patch.listFixedBugs.map( it => ({",
        "\t\t\t\tpersistenceId_string: it.persistenceId_string !== undefined ? it.persistenceId_string : null",
        "\t\t\t}))",
        "\t\t}",
        "\t}",
        "}"
      ],
      "exposed" : false
    },
    "context" : {
      "type" : "url",
      "value" : [
        "../API/bpm/userTask/{{taskId}}/context"
      ],
      "exposed" : false
    },
    "patch_listFixedBugs" : {
      "type" : "url",
      "value" : [
        "{{patch|lazyRef:'listFixedBugs'}}"
      ],
      "exposed" : false
    },
    "taskId" : {
      "type" : "urlparameter",
      "value" : [
        "id"
      ],
      "exposed" : false
    }
  },
  "hasValidationError" : false,
  "uuid" : "7ce49f5c-db84-4721-aeae-667fe473a221",
  "type" : "form",
  "description" : "Page generated with Bonita UI designer"
}